mediafile/__init__.py
mediafile/constants.py
mediafile/exceptions.py
mediafile/fields.py
mediafile/storage/__init__.py
mediafile/storage/afs.py
mediafile/storage/ape.py
mediafile/storage/base.py
mediafile/storage/flac.py
mediafile/storage/mp3.py
mediafile/storage/mp4.py
mediafile/storage/vorbis.py
mediafile/utils/__init__.py
mediafile/utils/image.py
mediafile/utils/mutagen_wrapper.py
mediafile/utils/soundcheck.py
mediafile/utils/type_conversion.py
mediafile-0.14.0.dist-info/METADATA
mediafile-0.14.0.dist-info/WHEEL
mediafile-0.14.0.dist-info/licenses/LICENSE
mediafile-0.14.0.dist-info/RECORD
