Metadata-Version: 2.4
Name: mediafile
Version: 0.14.0
Summary: A simple, cross-format library for reading and writing media file metadata.
License-Expression: MIT
License-File: LICENSE
Author: Adrian Sampson
Author-email: adrian@radbox.org
Requires-Python: >=3.10
Classifier: Topic :: Multimedia :: Sound/Audio
Classifier: Environment :: Web Environment
Classifier: Programming Language :: Python :: 3.10
Classifier: Programming Language :: Python :: 3.11
Classifier: Programming Language :: Python :: 3.12
Classifier: Programming Language :: Python :: 3.13
Classifier: Programming Language :: Python :: Implementation :: PyPy
Provides-Extra: docs
Requires-Dist: filetype (>=1.2.0)
Requires-Dist: mutagen (>=1.46)
Requires-Dist: sphinx (>=7.4.7) ; extra == "docs"
Project-URL: Bug Tracker, https://github.com/beetbox/mediafile/issues
Project-URL: Documentation, https://mediafile.readthedocs.io
Project-URL: Hopepage, https://mediafile.readthedocs.io
Project-URL: Repository, https://github.com/beetbox/mediafile
